pywinpipe/README.md
pywinpipe/__init__.py
pywinpipe/requirements.txt
pywinpipe/thirdparty.json
pywinpipe-0.11.dist-info/LICENSE.rst
pywinpipe-0.11.dist-info/METADATA
pywinpipe-0.11.dist-info/WHEEL
pywinpipe-0.11.dist-info/top_level.txt
pywinpipe-0.11.dist-info/RECORD
