Metadata-Version: 2.1
Name: pywinpipe
Version: 0.11
Summary: pywinpipe - Fast data exchange between 2 processes (Windows only)
Home-page: https://github.com/hansalemaos/pywinpipe
Author: Johannes Fischer
Author-email: aulasparticularesdealemaosp@gmail.com
License: MIT
Keywords: pipes,windows,named pipes,share,data
Classifier: Development Status :: 4 - Beta
Classifier: Programming Language :: Python :: 3 :: Only
Classifier: Programming Language :: Python :: 3.10
Classifier: Topic :: Software Development :: Libraries :: Python Modules
Classifier: Topic :: Utilities
License-File: LICENSE.rst
